packagenkm/__init__.py
packagenkm/example.py
packagenkm-0.1.dist-info/LICENSE.txt
packagenkm-0.1.dist-info/METADATA
packagenkm-0.1.dist-info/WHEEL
packagenkm-0.1.dist-info/top_level.txt
packagenkm-0.1.dist-info/RECORD
